llvmlite/__init__.py
llvmlite/_version.py
llvmlite/utils.py
llvmlite/binding/__init__.py
llvmlite/binding/analysis.py
llvmlite/binding/common.py
llvmlite/binding/config.py
llvmlite/binding/context.py
llvmlite/binding/dylib.py
llvmlite/binding/executionengine.py
llvmlite/binding/ffi.py
llvmlite/binding/initfini.py
llvmlite/binding/libllvmlite.dylib
llvmlite/binding/linker.py
llvmlite/binding/module.py
llvmlite/binding/newpassmanagers.py
llvmlite/binding/object_file.py
llvmlite/binding/options.py
llvmlite/binding/orcjit.py
llvmlite/binding/targets.py
llvmlite/binding/typeref.py
llvmlite/binding/value.py
llvmlite/ir/__init__.py
llvmlite/ir/_utils.py
llvmlite/ir/builder.py
llvmlite/ir/context.py
llvmlite/ir/instructions.py
llvmlite/ir/module.py
llvmlite/ir/transforms.py
llvmlite/ir/types.py
llvmlite/ir/values.py
llvmlite/tests/__init__.py
llvmlite/tests/__main__.py
llvmlite/tests/customize.py
llvmlite/tests/refprune_proto.py
llvmlite/tests/test_binding.py
llvmlite/tests/test_ir.py
llvmlite/tests/test_refprune.py
llvmlite/tests/test_valuerepr.py
llvmlite-0.46.0.dist-info/licenses/LICENSE
llvmlite-0.46.0.dist-info/licenses/LICENSE.thirdparty
llvmlite-0.46.0.dist-info/METADATA
llvmlite-0.46.0.dist-info/WHEEL
llvmlite-0.46.0.dist-info/top_level.txt
llvmlite-0.46.0.dist-info/RECORD
