Metadata-Version: 2.4
Name: llvmlite
Version: 0.46.0
Summary: lightweight wrapper around basic LLVM functionality
Home-page: http://llvmlite.readthedocs.io
License-Expression: BSD-2-Clause AND Apache-2.0 WITH LLVM-exception
Project-URL: Source, https://github.com/numba/llvmlite
Classifier: Development Status :: 4 - Beta
Classifier: Intended Audience :: Developers
Classifier: Operating System :: OS Independent
Classifier: Programming Language :: Python
Classifier: Programming Language :: Python :: 3
Classifier: Programming Language :: Python :: 3.10
Classifier: Programming Language :: Python :: 3.11
Classifier: Programming Language :: Python :: 3.12
Classifier: Programming Language :: Python :: 3.13
Classifier: Programming Language :: Python :: 3.14
Classifier: Topic :: Software Development :: Code Generators
Classifier: Topic :: Software Development :: Compilers
Requires-Python: >=3.10
License-File: LICENSE
License-File: LICENSE.thirdparty
Dynamic: classifier
Dynamic: description
Dynamic: home-page
Dynamic: license-file
Dynamic: license-expression
Dynamic: project-url
Dynamic: requires-python
Dynamic: summary
